google_search_console_mcp_python/__init__.py
google_search_console_mcp_python/customtypes.py
google_search_console_mcp_python/gsc_client.py
google_search_console_mcp_python/server.py
google_search_console_mcp_python/settings.py
google_search_console_mcp_python-0.1.3.dist-info/WHEEL
google_search_console_mcp_python-0.1.3.dist-info/entry_points.txt
google_search_console_mcp_python-0.1.3.dist-info/METADATA
google_search_console_mcp_python-0.1.3.dist-info/RECORD
