Metadata-Version: 2.3
Name: google-search-console-mcp-python
Version: 0.1.3
Summary: MCP Server for Google Search Console API access
Keywords: mcp,google-search-console,ai,tools,seo
Author: Locomotive Agency
Author-email: Locomotive Agency <cloud@locomotive.agency>
License: MIT
Classifier: Development Status :: 4 - Beta
Classifier: Intended Audience :: Developers
Classifier: License :: OSI Approved :: MIT License
Classifier: Programming Language :: Python :: 3
Classifier: Programming Language :: Python :: 3.12
Classifier: Topic :: Software Development :: Libraries :: Python Modules
Classifier: Topic :: Internet :: WWW/HTTP :: Indexing/Search
Requires-Dist: fastmcp>=0.1.0
Requires-Dist: loguru>=0.7.3
Requires-Dist: pydantic>=2.0.0
Requires-Dist: pydantic-settings>=2.0.0
Requires-Dist: google-api-python-client>=2.0.0
Requires-Dist: google-auth>=2.0.0
Requires-Dist: google-auth-oauthlib>=1.0.0
Requires-Dist: google-auth-httplib2>=0.2.0
Requires-Python: >=3.12
Project-URL: homepage, https://github.com/locomotive-agency/google-search-console-mcp-python
Project-URL: repository, https://github.com/locomotive-agency/google-search-console-mcp-python
